pychartweb/__init__.py
pychartweb/base2.tpl
pychartweb/chart2.js
pychartweb/pychart.py
pychartweb-1.1.1.dist-info/LICENSE
pychartweb-1.1.1.dist-info/METADATA
pychartweb-1.1.1.dist-info/WHEEL
pychartweb-1.1.1.dist-info/top_level.txt
pychartweb-1.1.1.dist-info/RECORD
