Metadata-Version: 2.1
Name: pychartweb
Version: 1.1.1
Summary: Display Graph
Home-page: UNKNOWN
Author: Harsh
Author-email: <singhharshhs586@gmail.com>
License: UNKNOWN
Keywords: python,chart.js,show chart
Platform: UNKNOWN
Classifier: Development Status :: 1 - Planning
Classifier: Intended Audience :: Developers
Classifier: Programming Language :: Python :: 3
Classifier: Operating System :: Unix
Classifier: Operating System :: MacOS :: MacOS X
Classifier: Operating System :: Microsoft :: Windows
License-File: LICENSE
Requires-Dist: bottle
